mangrove_surface/__init__.py
mangrove_surface/_version.py
mangrove_surface/logger.py
mangrove_surface/misc.py
mangrove_surface/api/__init__.py
mangrove_surface/api/classifier.py
mangrove_surface/api/classifier_evaluation_report.py
mangrove_surface/api/client_rest.py
mangrove_surface/api/collection.py
mangrove_surface/api/dataset.py
mangrove_surface/api/export.py
mangrove_surface/api/feature_set.py
mangrove_surface/api/license.py
mangrove_surface/api/project.py
mangrove_surface/api/token.py
mangrove_surface/api/user.py
mangrove_surface/api/version.py
mangrove_surface/wrapper/__init__.py
mangrove_surface/wrapper/classifier.py
mangrove_surface/wrapper/classifier_evaluation_report.py
mangrove_surface/wrapper/collection.py
mangrove_surface/wrapper/dataset.py
mangrove_surface/wrapper/export.py
mangrove_surface/wrapper/feature_set.py
mangrove_surface/wrapper/misc.py
mangrove_surface/wrapper/project.py
mangrove_surface/wrapper/schema.py
mangrove_surface_sdk-1.0.0.dist-info/METADATA
mangrove_surface_sdk-1.0.0.dist-info/RECORD
mangrove_surface_sdk-1.0.0.dist-info/WHEEL
mangrove_surface_sdk-1.0.0.dist-info/top_level.txt
