Metadata-Version: 2.1
Name: mangrove-surface-sdk
Version: 1.0.0
Summary: Mangrove Surface SDK
Home-page: https://github.com/mangroveai/mangrove-surface-python-sdk
Author: Mangrove
Author-email: contact@mangrove.ai
License: MIT
Platform: UNKNOWN
Classifier: Development Status :: 5 - Production/Stable
Classifier: Intended Audience :: Developers
Classifier: License :: OSI Approved :: MIT License
Classifier: Programming Language :: Python :: 2
Classifier: Programming Language :: Python :: 3
Requires-Dist: requests (>=2.12.3)
Requires-Dist: requests-toolbelt (>=0.7.0)
Requires-Dist: clint (>=0.5.1)
Requires-Dist: humanize (>=0.5.1)
Requires-Dist: funcsigs (>=1.0.2)
Requires-Dist: boto3 (>=1.4.4)
